bs_db_migration/__init__.py
bs_db_migration/config.py
bs_db_migration/domain_dictionary.py
bs_db_migration/ms2postgres.py
bs_db_migration/ms2postgres_type_mapping.py
bs_db_migration/common/__init__.py
bs_db_migration/common/debug.py
bs_db_migration/logger/__init__.py
bs_db_migration/logger/logger.py
bs_db_migration-0.2.2.dist-info/LICENSE
bs_db_migration-0.2.2.dist-info/METADATA
bs_db_migration-0.2.2.dist-info/WHEEL
bs_db_migration-0.2.2.dist-info/top_level.txt
bs_db_migration-0.2.2.dist-info/RECORD
