Metadata-Version: 2.1
Name: bs-db-migration
Version: 0.2.2
Summary: BS DB Migration
Home-page: https://github.com/vincent841/ms2postgres.git
Author: Jinwon Choi
Author-email: jinwon@hatiolab.com
License: MIT
Keywords: database migration
Classifier: Intended Audience :: Developers
Classifier: License :: OSI Approved :: MIT License
Classifier: Natural Language :: English
Classifier: Operating System :: OS Independent
Classifier: Programming Language :: Python :: 3.8
Classifier: Programming Language :: Python :: 3.9
Classifier: Topic :: Software Development :: Libraries :: Python Modules
License-File: LICENSE
Requires-Dist: psycopg2
Requires-Dist: pymssql
Requires-Dist: pyyaml
